binance_sdk_wallet/__init__.py
binance_sdk_wallet/metadata.py
binance_sdk_wallet/rest_api/__init__.py
binance_sdk_wallet/rest_api/api/__init__.py
binance_sdk_wallet/rest_api/api/account_api.py
binance_sdk_wallet/rest_api/api/asset_api.py
binance_sdk_wallet/rest_api/api/capital_api.py
binance_sdk_wallet/rest_api/api/others_api.py
binance_sdk_wallet/rest_api/api/travel_rule_api.py
binance_sdk_wallet/rest_api/models/__init__.py
binance_sdk_wallet/rest_api/models/account_api_trading_status_response.py
binance_sdk_wallet/rest_api/models/account_api_trading_status_response_data.py
binance_sdk_wallet/rest_api/models/account_api_trading_status_response_data_trigger_condition.py
binance_sdk_wallet/rest_api/models/account_info_response.py
binance_sdk_wallet/rest_api/models/account_status_response.py
binance_sdk_wallet/rest_api/models/all_coins_information_response.py
binance_sdk_wallet/rest_api/models/all_coins_information_response_inner.py
binance_sdk_wallet/rest_api/models/all_coins_information_response_inner_network_list_inner.py
binance_sdk_wallet/rest_api/models/asset_detail_response.py
binance_sdk_wallet/rest_api/models/asset_detail_response_ctr.py
binance_sdk_wallet/rest_api/models/asset_detail_response_sky.py
binance_sdk_wallet/rest_api/models/asset_dividend_record_response.py
binance_sdk_wallet/rest_api/models/asset_dividend_record_response_rows_inner.py
binance_sdk_wallet/rest_api/models/broker_withdraw_response.py
binance_sdk_wallet/rest_api/models/check_questionnaire_requirements_response.py
binance_sdk_wallet/rest_api/models/daily_account_snapshot_response.py
binance_sdk_wallet/rest_api/models/daily_account_snapshot_response_snapshot_vos_inner.py
binance_sdk_wallet/rest_api/models/daily_account_snapshot_response_snapshot_vos_inner_data.py
binance_sdk_wallet/rest_api/models/daily_account_snapshot_response_snapshot_vos_inner_data_assets_inner.py
binance_sdk_wallet/rest_api/models/daily_account_snapshot_response_snapshot_vos_inner_data_balances_inner.py
binance_sdk_wallet-7.0.0.dist-info/METADATA
binance_sdk_wallet-7.0.0.dist-info/WHEEL
binance_sdk_wallet-7.0.0.dist-info/licenses/LICENCE
binance_sdk_wallet-7.0.0.dist-info/RECORD
